bofire_converters/__init__.py
bofire_converters/opti_to_domain.py
bofire_converters/version.py
bofire_converters-0.0.4.dist-info/licenses/LICENSE
bofire_converters-0.0.4.dist-info/METADATA
bofire_converters-0.0.4.dist-info/WHEEL
bofire_converters-0.0.4.dist-info/top_level.txt
bofire_converters-0.0.4.dist-info/RECORD
