Metadata-Version: 2.4
Name: bofire_converters
Version: 0.0.4
License: BSD 3-Clause License
Project-URL: Homepage, https://github.com/experimental-design/bofire-converters
Classifier: Development Status :: 1 - Planning
Classifier: Programming Language :: Python :: 3 :: Only
Classifier: License :: OSI Approved :: BSD License
Classifier: Topic :: Scientific/Engineering
Classifier: Intended Audience :: Science/Research
Classifier: Intended Audience :: Developers
Requires-Python: >=3.10
License-File: LICENSE
Requires-Dist: mopti>=0.10.10
Requires-Dist: bofire>=0.2.0
Provides-Extra: test
Requires-Dist: pytest>=8.1.1; extra == "test"
Dynamic: license-file
